nous_llm/__init__.py
nous_llm/py.typed
nous_llm/adapters/__init__.py
nous_llm/adapters/anthropic_adapter.py
nous_llm/adapters/base.py
nous_llm/adapters/gemini_adapter.py
nous_llm/adapters/openai_adapter.py
nous_llm/adapters/openrouter_adapter.py
nous_llm/adapters/protocol.py
nous_llm/adapters/xai_adapter.py
nous_llm/core/__init__.py
nous_llm/core/adapters.py
nous_llm/core/client.py
nous_llm/core/exceptions.py
nous_llm/core/interface.py
nous_llm/core/models.py
nous_llm/core/registry.py
nous_llm/core/token_validator.py
nous_llm-0.3.0.dist-info/METADATA
nous_llm-0.3.0.dist-info/WHEEL
nous_llm-0.3.0.dist-info/licenses/LICENSE
nous_llm-0.3.0.dist-info/RECORD
