Metadata-Version: 2.4
Name: nous-llm
Version: 0.3.0
Summary: Intelligent No Frills LLM Router - A unified interface for multiple LLM providers
Project-URL: Homepage, https://github.com/amod-ml/nous-llm
Project-URL: Repository, https://github.com/amod-ml/nous-llm
Project-URL: Documentation, https://github.com/amod-ml/nous-llm#readme
Project-URL: Bug Reports, https://github.com/amod-ml/nous-llm/issues
Author-email: Amod ML <amodsahabandu@icloud.com>
License: MPL-2.0
License-File: LICENSE
Keywords: ai,anthropic,gemini,llm,ml,openai,openrouter,xai
Classifier: Development Status :: 4 - Beta
Classifier: Intended Audience :: Developers
Classifier: License :: OSI Approved :: Mozilla Public License 2.0 (MPL 2.0)
Classifier: Programming Language :: Python :: 3
Classifier: Programming Language :: Python :: 3.12
Classifier: Programming Language :: Python :: 3.13
Classifier: Topic :: Scientific/Engineering :: Artificial Intelligence
Classifier: Topic :: Software Development :: Libraries :: Python Modules
Requires-Python: >=3.12
Requires-Dist: anyio<5.0.0,>=4.10.0
Requires-Dist: httpx<1.0.0,>=0.28.0
Requires-Dist: pydantic<3.0.0,>=2.0.0
Requires-Dist: tenacity<11.0.0,>=9.0.0
Provides-Extra: all
Requires-Dist: anthropic<1.0.0,>=0.64.0; extra == 'all'
Requires-Dist: google-genai<2.0.0,>=0.8.0; extra == 'all'
Requires-Dist: openai<2.0.0,>=1.101.0; extra == 'all'
Requires-Dist: xai-sdk<3.0.0,>=1.1.0; extra == 'all'
Provides-Extra: anthropic
Requires-Dist: anthropic<1.0.0,>=0.64.0; extra == 'anthropic'
Provides-Extra: dev
Requires-Dist: faker<30.0.0,>=20.0.0; extra == 'dev'
Requires-Dist: mypy<2.0.0,>=1.17.0; extra == 'dev'
Requires-Dist: pytest-asyncio<1.0.0,>=0.24.0; extra == 'dev'
Requires-Dist: pytest-cov<6.0.0,>=4.0.0; extra == 'dev'
Requires-Dist: pytest-httpx<1.0.0,>=0.32.0; extra == 'dev'
Requires-Dist: pytest<9.0.0,>=8.4.0; extra == 'dev'
Requires-Dist: python-dotenv<2.0.0,>=1.1.0; extra == 'dev'
Requires-Dist: respx<1.0.0,>=0.21.0; extra == 'dev'
Requires-Dist: ruff<1.0.0,>=0.12.0; extra == 'dev'
Provides-Extra: gemini
Requires-Dist: google-genai<2.0.0,>=0.8.0; extra == 'gemini'
Provides-Extra: openai
Requires-Dist: openai<2.0.0,>=1.101.0; extra == 'openai'
Provides-Extra: openrouter
Requires-Dist: openai<2.0.0,>=1.101.0; extra == 'openrouter'
Provides-Extra: xai
Requires-Dist: xai-sdk<3.0.0,>=1.1.0; extra == 'xai'
